pylookfor/__init__.py
pylookfor-0.0.1.dist-info/LICENSE
pylookfor-0.0.1.dist-info/METADATA
pylookfor-0.0.1.dist-info/WHEEL
pylookfor-0.0.1.dist-info/top_level.txt
pylookfor-0.0.1.dist-info/RECORD
