Metadata-Version: 2.1
Name: pylookfor
Version: 0.0.1
Summary: A lightweight module searching methods in the current python environment by keywords
Home-page: https://github.com/KangqingYe/pylookfor
Author: yekangq
Author-email: yekangq@sjtu.edu.cn
License: UNKNOWN
Platform: UNKNOWN
Classifier: Programming Language :: Python :: 3
Classifier: License :: OSI Approved :: MIT License
Classifier: Operating System :: OS Independent
Requires-Python: >=3.6
